agent.py
songsearch_agent-0.3.1.dist-info/METADATA
songsearch_agent-0.3.1.dist-info/WHEEL
songsearch_agent-0.3.1.dist-info/entry_points.txt
songsearch_agent-0.3.1.dist-info/top_level.txt
songsearch_agent-0.3.1.dist-info/RECORD
