Metadata-Version: 2.1
Name: songsearch-agent
Version: 0.3.1
Summary: Helps SongSearch download
Home-page: UNKNOWN
Author: Peter Bengtsson
Author-email: mail@peterbe.com
License: MIT
Platform: UNKNOWN
Requires-Dist: requests
Provides-Extra: dev
Requires-Dist: flake8 ; extra == 'dev'
Requires-Dist: black ; extra == 'dev'
